apssh/.pylintrc
apssh/__init__.py
apssh/__main__.py
apssh/cli.py
apssh/commands.py
apssh/config.py
apssh/deferred.py
apssh/formatters.py
apssh/keys.py
apssh/nodes.py
apssh/parse-ssh-config.py
apssh/service.py
apssh/ssh-like-config
apssh/sshjob.py
apssh/sshproxy.py
apssh/targets.py
apssh/topology.py
apssh/util.py
apssh/version.py
apssh/yaml_loader.py
apssh-0.27.0.dist-info/METADATA
apssh-0.27.0.dist-info/WHEEL
apssh-0.27.0.dist-info/entry_points.txt
apssh-0.27.0.dist-info/licenses/LICENSE
apssh-0.27.0.dist-info/RECORD
