Metadata-Version: 2.4
Name: apssh
Version: 0.27.0
Summary: Asynchroneous Parallel ssh
Project-URL: Homepage, http://github.com/parmentelat/apssh
Project-URL: Documentation, http://apssh.readthedocs.io/
Author-email: Thierry Parmentelat <thierry.parmentelat@inria.fr>
License: CC BY-SA 4.0
License-File: LICENSE
Keywords: asyncio,parallel ssh,remote shell,ssh
Requires-Python: >=3.10
Requires-Dist: asynciojobs
Requires-Dist: asyncssh
Requires-Dist: jinja2
Requires-Dist: pyyaml
Provides-Extra: readthedocs
Requires-Dist: myst-parser; extra == 'readthedocs'
Requires-Dist: recommonmark; extra == 'readthedocs'
Requires-Dist: sphinx-autodoc-typehints; extra == 'readthedocs'
Provides-Extra: tests
Requires-Dist: psutil; extra == 'tests'
Requires-Dist: pytest; extra == 'tests'
